nxpsdk/__init__.py
nxpsdk/cpp.cp38-win_amd64.pyd
nxpsdk/nxpsdk.dll
nxpsdk/nxpsdk.lib
nxpsdk/py.typed
nxpsdk-2.0.3.dist-info/LICENSE
nxpsdk-2.0.3.dist-info/METADATA
nxpsdk-2.0.3.dist-info/WHEEL
nxpsdk-2.0.3.dist-info/top_level.txt
nxpsdk-2.0.3.dist-info/RECORD
