Metadata-Version: 2.1
Name: nxpsdk
Version: 2.0.3
Summary: Native Experience SDK from RealEyes
Home-page: UNKNOWN
Author: Realeyes
Author-email: daniel@realeyesit.com
License: UNKNOWN
Platform: UNKNOWN
Requires-Dist: numpy >=1.10.0
